reuters_style/__init__.py
reuters_style-0.0.5.dist-info/LICENSE
reuters_style-0.0.5.dist-info/METADATA
reuters_style-0.0.5.dist-info/WHEEL
reuters_style-0.0.5.dist-info/top_level.txt
reuters_style-0.0.5.dist-info/RECORD
