Metadata-Version: 2.1
Name: reuters-style
Version: 0.0.5
Summary: Format dates, numbers and text to conform with the Reuters Style Guide, the standards that guide the world's largest independent newsroom
Home-page: https://palewi.re/docs/reuters-style/
Author: Ben Welsh
Author-email: b@palewi.re
License: MIT
Project-URL: Maintainer, https://github.com/palewire
Project-URL: Source, https://www.github.com/palewire/reuters-style
Project-URL: Tracker, https://www.github.com/palewire/reuters-style
Classifier: Development Status :: 5 - Production/Stable
Classifier: Programming Language :: Python
Classifier: Programming Language :: Python :: 3
Classifier: Programming Language :: Python :: 3.9
Classifier: Programming Language :: Python :: 3.10
Classifier: Programming Language :: Python :: 3.11
Classifier: License :: OSI Approved :: MIT License
License-File: LICENSE
